[
    {
        "collection": "ahmad",
        "bookNumber": "744",
        "chapterTitleArabic": "حديث أحمر بن جزي",
        "chapterTitleFrench": "Musnad - Chapitre 744",
        "hadithNumber": "19012",
        "arabicText": "حَدِيثُ أَحْمَرَ بْنِ جَزِيٍّ، ١٩٠١٢ - حَدَّثَنَا عَبْدُ الرَّحْمَنِ بْنُ مَهْدِيٍّ، حَدَّثَنَا عَبَّادُ بْنُ رَاشِدٍ، قَالَ: سَمِعْتُ الْحَسَنَ يَقُولُ: حَدَّثَنَا أَحْمَرُ بْنُ جَزِيٍّ، صَاحِبُ رَسُولِ اللهِ صَلَّى اللهُ عَلَيْهِ وَسَلَّمَ قَالَ: \" إِنْ كُنَّا لَنَأْوِي إِلَى رَسُولِ اللهِ صَلَّى اللهُ عَلَيْهِ وَسَلَّمَ، مِمَّا يُجَافِي مِرْفَقَيْهِ عَنْ جَنْبَيْهِ إِذَا سَجَدَ \" (١)، ،",
        "frenchText": "",
        "reference": {
            "book": "744",
            "hadith": "19012"
        }
    }
]