[
    {
        "collection": "ahmad",
        "bookNumber": "1056",
        "chapterTitleArabic": "حديث رجل من تغلب",
        "chapterTitleFrench": "Musnad - Chapitre 1056",
        "hadithNumber": "23483",
        "arabicText": "حَدِيثُ رَجُلٍ مِنْ تَغْلِبَ، ٢٣٤٨٣ - حَدَّثَنَا جَرِيرٌ، عَنْ عَطَاءِ بْنِ السَّائِبِ، عَنْ حَرْبِ بْنِ هِلَالٍ الثَّقَفِيِّ، عَنْ أَبِي أُمَّيَّةَ رَجُلٍ مِنْ تَغْلِبَ، أَنَّهُ سَمِعَ رَسُولَ اللهِ صَلَّى اللهُ عَلَيْهِ وَسَلَّمَ يَقُولُ: \" لَيْسَ عَلَى الْمُسْلِمِينَ عُشُورٌ إِنَّمَا الْعُشُورُ عَلَى الْيَهُودِ وَالنَّصَارَى \" (١)، ،",
        "frenchText": "",
        "reference": {
            "book": "1056",
            "hadith": "23483"
        }
    }
]