[
    {
        "collection": "ahmad",
        "bookNumber": "1058",
        "chapterTitleArabic": "حديث رجل من الأنصار",
        "chapterTitleFrench": "Musnad - Chapitre 1058",
        "hadithNumber": "23485",
        "arabicText": "حَدِيثُ رَجُلٍ مِنَ الْأَنْصَارِ، ٢٣٤٨٥ - حَدَّثَنَا إِسْمَاعِيلُ، حَدَّثَنِي حَجَّاجٌ الصَّوَّافُ، عَنْ يَحْيَى بْنِ أَبِي كَثِيرٍ، عَنِ الْحَضْرَمِيِّ بْنِ لَاحِقٍ، عَنْ رَجُلٍ مِنَ الْأَنْصَارِ، أَنَّ رَسُولَ اللهِ صَلَّى اللهُ عَلَيْهِ وَسَلَّمَ قَالَ: \" إِذَا وَجَدَ أَحَدُكُمُ الْقَمْلَةَ فِي ثَوْبِهِ فَلْيَصُرَّهَا وَلَا يُلْقِهَا فِي الْمَسْجِدِ \" (١)، ،",
        "frenchText": "",
        "reference": {
            "book": "1058",
            "hadith": "23485"
        }
    }
]